petboa/__init__.py
petboa/expressions.py
petboa/modelwrappers.py
petboa/omkm.py
petboa/optimizer.py
petboa/plots.py
petboa/reactor.py
petboa/utils.py
petboa-0.1.1.dist-info/LICENSE.md
petboa-0.1.1.dist-info/METADATA
petboa-0.1.1.dist-info/WHEEL
petboa-0.1.1.dist-info/top_level.txt
petboa-0.1.1.dist-info/RECORD
